MANIFEST.in
setup.py
bin/jokes
bin/ljmail
bin/ljmail-generate-config
lj_commons/__init__.py
lj_commons/command_parse.py
lj_commons/config.py
lj_commons/mail.py
lj_commons/mail_config.ini
lj_commons/test.py
lj_commons/text.py
lj_commons.egg-info/PKG-INFO
lj_commons.egg-info/SOURCES.txt
lj_commons.egg-info/dependency_links.txt
lj_commons.egg-info/not-zip-safe
lj_commons.egg-info/requires.txt
lj_commons.egg-info/top_level.txt