Metadata-Version: 1.0
Name: lj-commons
Version: 0.4
Summary: The common parameters, methods and classes for Luojilab Pythonists
Home-page: UNKNOWN
Author: Fu Jian
Author-email: fujian_en@126.com
License: MIT
Platform: UNKNOWN
